simulate/__init__.py
simulate/_fastwfc.cpython-310-darwin.so
simulate/_vhacd.cpython-310-darwin.so
simulate/config.py
simulate/scene.py
simulate/assets/__init__.py
simulate/assets/action_mapping.py
simulate/assets/actors.py
simulate/assets/actuator.py
simulate/assets/articulation_body.py
simulate/assets/asset.py
simulate/assets/camera.py
simulate/assets/collider.py
simulate/assets/gltf_export.py
simulate/assets/gltf_extension.py
simulate/assets/gltf_import.py
simulate/assets/light.py
simulate/assets/material.py
simulate/assets/object.py
simulate/assets/physic_material.py
simulate/assets/reward_functions.py
simulate/assets/rigid_body.py
simulate/assets/sensors.py
simulate/assets/utils.py
simulate/assets/anytree/__init__.py
simulate/assets/anytree/abstractiter.py
simulate/assets/anytree/exceptions.py
simulate/assets/anytree/nodemixin.py
simulate/assets/anytree/preorderiter.py
simulate/assets/anytree/render.py
simulate/assets/gltflib/__init__.py
simulate/assets/gltflib/__version__.py
simulate/assets/gltflib/gltf.py
simulate/assets/gltflib/gltf_resource.py
simulate/assets/gltflib/enums/__init__.py
simulate/assets/gltflib/enums/accessor_type.py
simulate/assets/gltflib/enums/alpha_mode.py
simulate/assets/gltflib/enums/animation_target_path.py
simulate/assets/gltflib/enums/buffer_target.py
simulate/assets/gltflib/enums/camera_type.py
simulate/assets/gltflib/enums/component_type.py
simulate/assets/gltflib/enums/interpolation.py
simulate/assets/gltflib/enums/primitive_mode.py
simulate/assets/gltflib/enums/rigidbody_constraints.py
simulate/assets/gltflib/models/__init__.py
simulate/assets/gltflib/models/accessor.py
simulate/assets/gltflib/models/animation.py
simulate/assets/gltflib/models/animation_sampler.py
simulate/assets/gltflib/models/asset.py
simulate/assets/gltflib/models/attributes.py
simulate/assets/gltflib/models/base_model.py
simulate/assets/gltflib/models/buffer.py
simulate/assets/gltflib/models/buffer_view.py
simulate/assets/gltflib/models/camera.py
simulate-0.1.2.dist-info/LICENSE
simulate-0.1.2.dist-info/METADATA
simulate-0.1.2.dist-info/WHEEL
simulate-0.1.2.dist-info/top_level.txt
simulate-0.1.2.dist-info/RECORD
