Metadata-Version: 2.1
Name: simulate
Version: 0.1.2
Summary: HuggingFace community-driven open-source library of simulation environments
Home-page: https://github.com/huggingface/simulate
Download-URL: https://github.com/huggingface/simulate/tags
Author: HuggingFace Inc.
Author-email: thomas@huggingface.co
License: Apache 2.0
Keywords: simulation environments synthetic data datasets machine learning
Platform: UNKNOWN
Classifier: Development Status :: 5 - Production/Stable
Classifier: Intended Audience :: Developers
Classifier: Intended Audience :: Education
Classifier: Intended Audience :: Science/Research
Classifier: License :: OSI Approved :: Apache Software License
Classifier: Operating System :: OS Independent
Classifier: Programming Language :: Python :: 3
Classifier: Programming Language :: Python :: 3.8
Classifier: Programming Language :: Python :: 3.9
Classifier: Programming Language :: Python :: 3.10
Classifier: Topic :: Scientific/Engineering :: Artificial Intelligence
Requires-Python: >=3.8
License-File: LICENSE
Requires-Dist: dataclasses-json
Requires-Dist: numpy (>=1.18)
Requires-Dist: vtk (>=9.0)
Requires-Dist: pyvista (>=0.35)
Requires-Dist: huggingface-hub (>=0.10)
Requires-Dist: pybind11 (>=2.10.0)
Requires-Dist: scikit-build (>=0.5)
Provides-Extra: dev
Requires-Dist: gym (==0.21.0) ; extra == 'dev'
Requires-Dist: stable-baselines3 ; extra == 'dev'
Requires-Dist: pyvistaqt ; extra == 'dev'
Requires-Dist: pyqt5 ; extra == 'dev'
Requires-Dist: pytest ; extra == 'dev'
Requires-Dist: pytest-xdist ; extra == 'dev'
Requires-Dist: gym ; extra == 'dev'
Requires-Dist: black[jupyter] (~=22.0) ; extra == 'dev'
Requires-Dist: flake8 (>=3.8.3) ; extra == 'dev'
Requires-Dist: isort (>=5.0.0) ; extra == 'dev'
Requires-Dist: pyyaml (>=5.3.1) ; extra == 'dev'
Provides-Extra: docs
Requires-Dist: s3fs ; extra == 'docs'
Provides-Extra: quality
Requires-Dist: black[jupyter] (~=22.0) ; extra == 'quality'
Requires-Dist: flake8 (>=3.8.3) ; extra == 'quality'
Requires-Dist: isort (>=5.0.0) ; extra == 'quality'
Requires-Dist: pyyaml (>=5.3.1) ; extra == 'quality'
Provides-Extra: rl
Requires-Dist: gym (==0.21.0) ; extra == 'rl'
Provides-Extra: sb3
Requires-Dist: gym (==0.21.0) ; extra == 'sb3'
Requires-Dist: stable-baselines3 ; extra == 'sb3'
Provides-Extra: test
Requires-Dist: pytest ; extra == 'test'
Requires-Dist: pytest-xdist ; extra == 'test'
Requires-Dist: gym ; extra == 'test'
Requires-Dist: stable-baselines3 ; extra == 'test'
